README.md
setup.py
ftest/__init__.py
ftest/__main__.py
ftest/lang.py
ftest/logger.py
ftest/processes.py
ftest/register.py
ftest/supervisor.py
ftest/version.py
ftest/vio.py
ftest.egg-info/PKG-INFO
ftest.egg-info/SOURCES.txt
ftest.egg-info/dependency_links.txt
ftest.egg-info/entry_points.txt
ftest.egg-info/requires.txt
ftest.egg-info/top_level.txt